{
  "valorant": {
    "subscribers": 342,
    "total_views": 7156,
    "video_count": 8,
    "checked_at": "2026-05-24"
  },
  "marvel-rivals": {
    "subscribers": 0,
    "total_views": 1,
    "video_count": 0,
    "checked_at": "2026-05-22"
  },
  "the-finals": {
    "subscribers": 0,
    "total_views": 55,
    "video_count": 0,
    "checked_at": "2026-05-22"
  },
  "rocket-league": {
    "subscribers": 1,
    "total_views": 256,
    "video_count": 5,
    "checked_at": "2026-05-24"
  },
  "apex-legends": {
    "subscribers": 0,
    "total_views": 99,
    "video_count": 6,
    "checked_at": "2026-05-24"
  },
  "r6-siege": {
    "subscribers": 2,
    "total_views": 4891,
    "video_count": 7,
    "checked_at": "2026-05-24"
  }
}